src/rtl/numeric_code_detonator.v
////////////////////////////////////////////////////////////////////////////////
// Company: nudt
// Engineer: huang junzhe
//
// Create Date: 2022/11/07                        
// Design Name: numeric_code_detonator
// Module Name: numeric_code_detonator
// Target Device: PYNQ-Z2
// Tool versions: vivado 18.2
// Description:
// 1. The digital code detonator adopts 4 decimal numbers, 
//    and the currently entered number is displayed through the digital tube 
//    when entering the password.
// 2. When the 4-digit password is entered correctly, the system can 
//    start the detonation device correctly; 
//    The system alerts you when a password is entered incorrectly 
//    (one more, one less, or incorrect).
// 3. After the system reset, it is in the waiting state after the system reset,
//    press the waiting state, press the Ready button, 
//    and you are ready to enter the password.
// 4. After the password is entered correctly, it can be detonated 
//    after the password is entered correctly
// 5. When the password is entered incorrectly, the system gives an alarm 
//    When the password is entered incorrectly, the system gives an alarm 
//    and the red light flashes, at this time, Ready and Wait_t are invalid 
//    and must be reset to the waiting state by the security personnel.
// 6. After the detonation event, the system shall return to the waiting state, 
//    and after the detonation event, the system shall return to the waiting state
// 7. Ten numeric keys are entered as a password
//
// Dependencies: 
//
// Revision:
// 3.0
////////////////////////////////////////////////////////////////////////////////

module numeric_code_detonator #(
  parameter ORIGIN_PASSPORT = 16'h2580 // initial passport
)(
  input                 clk,
  input                 rst,
  input                 wait_t,
  input                 setup,
  input                 ready,
  input                 fire,
  input                 sure,
  input[3:0]            A,        // passport input
  input                 confirm,  // passport confirm
  output                lt,       // green led
  output                bt,       // yellow led
  output                rt_en,    // red led
  output                disp_en,  // Nixie tube enable
  output reg[15:0]      passport  // current passport input, connect to Nixie tube
);

localparam WAIT = 4'd0, READY = 4'd1, INPUT1 = 4'd2, INPUT2 = 4'd3, INPUT3 = 4'd4, INPUT4 = 4'd5, CHECK = 4'd6, ERROR = 4'd7, OK = 4'd8, FIRE = 4'd9;

reg[3:0] current_state, next_state;
reg[31:0] cnt;
reg[3:0] ptr; // The current password input pointer
wire any_input = fire | ready | sure | wait_t;

always @(*) begin
  case (current_state)
    WAIT: begin
      if (fire)
        next_state = ERROR;
      else if (ready)
        next_state = READY;
      else
        next_state = WAIT;
    end
    READY: begin
      if (sure || fire)
        next_state = ERROR;
      else if (wait_t)
        next_state = WAIT;
      else if (confirm)
        next_state = INPUT1;
      else
        next_state = READY;
    end
    INPUT1: begin
      if (fire || sure)
        next_state = ERROR;
      else if (wait_t)
        next_state = WAIT;
      else if (confirm)
        next_state = INPUT2;
      else
        next_state = INPUT1;
    end
    INPUT2: begin
      if (fire || sure)
        next_state = ERROR;
      else if (wait_t)
        next_state = WAIT;
      else if (confirm)
        next_state = INPUT3;
      else
        next_state = INPUT2;
    end
    INPUT3: begin
      if (fire || sure)
        next_state = ERROR;
      else if (wait_t)
        next_state = WAIT;
      else if (confirm)
        next_state = INPUT4;
      else
        next_state = INPUT3;
    end
    INPUT4: begin
      if (fire || confirm)
        next_state = ERROR;
      else if (wait_t)
        next_state = WAIT;
      else if (sure)
        next_state = CHECK;
      else
        next_state = INPUT4;
    end       
    CHECK: begin
      // check the passport
      if (passport == ORIGIN_PASSPORT)
        next_state = OK;
      else
        next_state = ERROR;
    end
    OK: begin
      next_state = fire ? FIRE : OK;
    end         
    FIRE: begin
      next_state = wait_t ? WAIT : FIRE;
    end
    ERROR: begin
      next_state = setup ? WAIT : ERROR;
    end
    default: next_state = WAIT;
  endcase
end

always @(posedge clk) begin
  if (rst)
    current_state <= WAIT;
  else
    current_state <= next_state;
end

// save the input number
always @(posedge clk) begin
  if (rst) begin
    passport <= 16'd0;
    ptr <= 4'd15;
  end
  else if (current_state == READY || current_state == INPUT1 || current_state == INPUT2 || current_state == INPUT3)
    if (confirm) begin
      passport[ptr -: 4] <= A;
      ptr <= ptr - 4'd4;
    end
    else begin
      passport <= passport;
      ptr <= ptr;
    end
  else if (current_state == INPUT4 || current_state == CHECK || current_state == OK) begin
    passport <= passport;
    ptr <= ptr;
  end
  else begin
    passport <= 16'd0;
    ptr <= 4'd15;
  end
end

assign rt_en = current_state == ERROR;
assign disp_en = current_state == INPUT1 || current_state == INPUT2 || current_state == INPUT3 || current_state == INPUT4 || current_state == CHECK;
assign lt = current_state == OK;
assign bt = current_state == FIRE;
endmodule

src/rtl/red_led.v
////////////////////////////////////////////////////////////////////////////////
// Company: nudt
// Engineer: huang junzhe
//
// Create Date: 2023/01/01                        
// Design Name: numeric_code_detonator
// Module Name: red_led
// Target Device: PYNQ-Z2
// Tool versions: vivado 18.2
// Description:
// fpga red led module
//
// Dependencies: 
//
// Revision:
// 1.0
////////////////////////////////////////////////////////////////////////////////

module red_led #(
	RT_CNT_MAX = 62_500_000 // 125MHZ 0.5s
)(
	input clk,
	input rst,

	input en,
	output rt
);

reg rt_tmp;
reg [31:0] cnt;

assign rt = en ? rt_tmp : 1'b0;

// count 0.5s
always @(posedge clk) begin
  if (rst)
    cnt <= 0;
  else if (en)
    cnt <= (cnt == RT_CNT_MAX - 1) ? 0 : cnt + 1;
  else
    cnt <= 0;
end

always @(posedge clk) begin
  if (rst)
    rt_tmp <= 1'b0;
  else if (cnt == RT_CNT_MAX - 1)
    rt_tmp <= ~rt_tmp;
  else
	rt_tmp <= rt_tmp;
end
endmodule

src/rtl/disp_ctrl.v
////////////////////////////////////////////////////////////////////////////////
// Company: nudt
// Engineer: huang junzhe
//
// Create Date: 2023/01/01                        
// Design Name: numeric_code_detonator
// Module Name: disp_num
// Target Device: PYNQ-Z2
// Tool versions: vivado 18.2
// Description:
// Digital tube control module
//
// Dependencies: 
//
// Revision:
// 1.0
////////////////////////////////////////////////////////////////////////////////

module disp_ctrl #(
  parameter DISP_COUNT = 50000
)(
  input           clk,
  input           rst,

  input           en,
  input[15:0]     data,
  output[3:0]     sel,
  output reg[6:0] m_disp
);

reg[3:0] sel_n;
reg[3:0] current_input;
reg[15:0] count;
reg clk_out;

assign sel = en ? ~sel_n : 4'b1111;

always@(posedge clk) begin
  if(rst) begin
    count <= 16'd0;
    clk_out <= 1'b1;
  end
  else begin
    if(count == DISP_COUNT - 1) begin
      clk_out <= ~clk_out;
      count <= 16'd0;
    end
    else
      count <= count + 16'd1;	
  end
end

always @(posedge clk_out) begin
  if (rst)
    sel_n <= 4'b1000;
  else if (en)
    sel_n <= sel_n == 4'b0001 ? 4'b1000 : (sel_n >> 1);
  else
    sel_n <= sel_n;
end

always @(*) begin
  case(current_input)
    0: m_disp = 7'b0000001;
    1: m_disp = 7'b1001111;
    2: m_disp = 7'b0010010;
    3: m_disp = 7'b0000110;
    4: m_disp = 7'b1001100;
    5: m_disp = 7'b0100100;
    6: m_disp = 7'b0100000;
    7: m_disp = 7'b0001111;
    8: m_disp = 7'b0000000;
    9: m_disp = 7'b0000100;
    default: m_disp = 7'b0000001;
  endcase
end

always @(*) begin
  case (sel)
    4'b0111: current_input = data[15:12];
    4'b1011: current_input = data[11:8];
    4'b1101: current_input = data[7:4];
    4'b1110: current_input = data[3:0];
    default: current_input = data[3:0];
  endcase
end
endmodule

src/rtl/key_debounce.v
////////////////////////////////////////////////////////////////////////////////
// Company: nudt
// Engineer: huang junzhe
//
// Create Date: 2022/11/07                        
// Design Name: numeric_code_detonator
// Module Name: key_debounce
// Target Device: PYNQ-Z2
// Tool versions: vivado 18.2
// Description:
// FPGA key debounce module
//
// Dependencies: 
//
// Revision:
// 1.0
////////////////////////////////////////////////////////////////////////////////

module key_debounce #(
  parameter KEY_CNT_MAX = 2_500_000 // 20ms
)(
  input               clk,
  input               rst,
  input               key,
  output              debounced_key
);

reg[31:0] cnt;
reg key_flag;
 
always @(posedge clk) begin
  if (rst)
    cnt <= 1'b0;
  else if (key == 1'b1)
    cnt <= cnt == (KEY_CNT_MAX - 1'b1) ? 32'd0 : cnt + 1;
  else
    cnt <= 16'd0;
end
 
always @(posedge clk) begin
  if (rst)
    key_flag <= 1'b0;
  else if (cnt == KEY_CNT_MAX - 1)
    key_flag <= 1'b1;
  else
    key_flag <= 1'b0;
end

assign debounced_key = key_flag;
endmodule

src/rtl/top.v
////////////////////////////////////////////////////////////////////////////////
// Company: nudt
// Engineer: huang junzhe
//
// Create Date: 2022/11/07                        
// Design Name: numeric_code_detonator
// Module Name: top
// Target Device: PYNQ-Z2
// Tool versions: vivado 18.2
// Description:
// top module of numeric_code_detonator
//
// Dependencies: 
//
// Revision:
// 2.0
////////////////////////////////////////////////////////////////////////////////

module top #(
  parameter KEY_CNT_MAX     = 625_000   ,
  parameter RT_CNT_MAX      = 62_500_000,
  parameter ORIGIN_PASSPORT = 16'h2580,
  parameter DISP_COUNT      = 50000
)(
  input         clk,
  input         rst,
  input         wait_t,
  input         setup,
  input         ready,
  input         fire,
  input         sure,
  input[3:0]    A,
  input         confirm,
  output[3:0]   sel,
  output        lt,
  output        bt,
  output        rt,
  output[6:0]   m_disp 
);

wire db_wait_t, db_setup, db_ready, db_fire, db_sure, db_confirm;
wire disp_en, rt_en;
wire[15:0] passport;

key_debounce #(
  .KEY_CNT_MAX  (KEY_CNT_MAX)
)wait_db (
  .clk            (clk      ),
  .rst            (rst      ),
  .key            (wait_t   ),
  .debounced_key  (db_wait_t)
);

key_debounce #(
  .KEY_CNT_MAX  (KEY_CNT_MAX)
)setup_db (
  .clk            (clk      ),
  .rst            (rst      ),
  .key            (setup    ),
  .debounced_key  (db_setup )
);

key_debounce #(
  .KEY_CNT_MAX  (KEY_CNT_MAX)
)ready_db (
  .clk            (clk      ),
  .rst            (rst      ),
  .key            (ready    ),
  .debounced_key  (db_ready )
);

key_debounce #(
  .KEY_CNT_MAX  (KEY_CNT_MAX)
)fire_db (
  .clk            (clk      ),
  .rst            (rst      ),
  .key            (fire     ),
  .debounced_key  (db_fire  )
);

key_debounce #(
  .KEY_CNT_MAX  (KEY_CNT_MAX)
)sure_db (
  .clk            (clk      ),
  .rst            (rst      ),
  .key            (sure     ),
  .debounced_key  (db_sure  )
);

key_debounce #(
  .KEY_CNT_MAX  (KEY_CNT_MAX)
)confirm_db (
  .clk            (clk        ),
  .rst            (rst        ),
  .key            (confirm    ),
  .debounced_key  (db_confirm )
);

disp_ctrl #(
  .DISP_COUNT   (DISP_COUNT)
)u_disp_ctrl (
  .clk            (clk        ),
  .rst            (rst        ),

  .en             (disp_en    ),
  .data           (passport   ),
  .sel            (sel        ),
  .m_disp         (m_disp     )
);

red_led #(
  .RT_CNT_MAX(RT_CNT_MAX)
)u_red_led (
  .clk            (clk        ),
  .rst            (rst        ),

  .en             (rt_en      ),
  .rt             (rt         )
);

numeric_code_detonator #(
  .ORIGIN_PASSPORT(ORIGIN_PASSPORT)
)numeric_code_detonator_inst (
  .clk            (clk        ),
  .rst            (rst        ),

  .wait_t         (db_wait_t  ),
  .setup          (db_setup   ),
  .ready          (db_ready   ),
  .fire           (db_fire    ),
  .sure           (db_sure    ),
  .A              (A          ),
  .confirm        (db_confirm ),
  .lt             (lt         ),
  .bt             (bt         ),
  .rt_en          (rt_en      ),
  .disp_en        (disp_en    ),
  .passport       (passport   )
);
endmodule

src/rtl/top_tb.v
`timescale 1ps/1ps

module top_tb;

reg clk, rst;
reg wait_t, setup, ready, fire, sure, confirm;
reg[3:0] A;
wire[3:0] sel;
wire lt, bt, rt;
wire[6:0] m_disp;

initial begin            
  $dumpfile("wave.vcd"); //生成的vcd文件名称
  $dumpvars(0, top_tb); //tb模块名称
end

initial begin
  clk <= 1'b0;
  forever #10 clk = ~clk;
end

initial begin
  rst <= 1'b1;
  #20
  rst <= 1'b0;
end

initial begin
  {wait_t, setup, ready, fire, sure, confirm} <= 6'b0;
  //----------------------------正确操作测试-------------------------------
  // 测试按键消抖
  @(posedge clk)
  ready <= 1'b1;
  @(posedge clk)
  ready <= 1'b0;
  repeat(3) begin
    @(posedge clk)
    ready <= 1'b1;
  end
  @(posedge clk)
  ready <= 1'b0;
  // 测试密码输入
  confirm <= 1'b1;
  repeat(3) begin
    @(posedge clk)
    confirm <= 1'b1;
  end
  @(posedge clk)
  A <= 4'd2;

  confirm <= 1'b1;
  repeat(3) begin
    @(posedge clk)
    confirm <= 1'b1;
  end
  @(posedge clk)
  A <= 4'd5;

  confirm <= 1'b1;
  repeat(3) begin
    @(posedge clk)
    confirm <= 1'b1;
  end
  @(posedge clk)
  A <= 4'd8;

  confirm <= 1'b1;
  repeat(3) begin
    @(posedge clk)
    confirm <= 1'b1;
  end
  @(posedge clk)
  A <= 4'd0;
  confirm <= 1'b0;

  // 密码确认
  sure <= 1'b1;
  repeat(3) begin
    @(posedge clk)
    sure <= 1'b1;
  end
  @(posedge clk)
  sure <= 1'b0;
  // 引爆
  fire <= 1'b1;
  repeat(3) begin
    @(posedge clk)
    fire <= 1'b1;
  end
  @(posedge clk)
  fire <= 1'b0;
  // 回到等待状态
  wait_t <= 1'b1;
  #200
  wait_t <= 1'b0;

  //----------------------------错误操作测试-------------------------------
  #200
  // 测试提前引爆进入错误状态
  ready <= 1'b1;
  repeat(3) begin
    @(posedge clk)
    ready <= 1'b1;
  end
  @(posedge clk)
  ready <= 1'b0;

  confirm <= 1'b1;
  repeat(3) begin
    @(posedge clk)
    confirm <= 1'b1;
  end
  @(posedge clk)
  confirm <= 1'b0;
  A <= 4'd2;

  fire <= 1'b1;
  repeat(3) begin
    @(posedge clk)
    fire <= 1'b1;
  end
  @(posedge clk)
  fire <= 1'b0;
  // 错误状态下等待信号无效
  wait_t <= 1'b1;
  repeat(3) begin
    @(posedge clk)
    wait_t <= 1'b1;
  end
  @(posedge clk)
  wait_t <= 1'b0;
  // 置位信号有效
  setup <= 1'b1;
  repeat(3) begin
    @(posedge clk)
    setup <= 1'b1;
  end
  @(posedge clk)
  setup <= 1'b0;

  // 测试少输入了密码
  ready <= 1'b1;
  repeat(3) begin
    @(posedge clk)
    ready <= 1'b1;
  end
  @(posedge clk)
  ready <= 1'b0;

  confirm <= 1'b1;
  repeat(3) begin
    @(posedge clk)
    confirm <= 1'b1;
  end
  @(posedge clk)
  confirm <= 1'b0;
  A <= 4'd2;

  sure <= 1'b1;
  repeat(3) begin
    @(posedge clk)
    sure <= 1'b1;
  end
  @(posedge clk)
  sure <= 1'b0;

  setup <= 1'b1;
  repeat(3) begin
    @(posedge clk)
    setup <= 1'b1;
  end
  @(posedge clk)
  setup <= 1'b0;

  // 测试多输入了密码
  ready <= 1'b1;
  repeat(3) begin
    @(posedge clk)
    ready <= 1'b1;
  end
  @(posedge clk)
  ready <= 1'b0;

  confirm <= 1'b1;
  repeat(3) begin
    @(posedge clk)
    confirm <= 1'b1;
  end
  @(posedge clk)
  A <= 4'd3;

  confirm <= 1'b1;
  repeat(3) begin
    @(posedge clk)
    confirm <= 1'b1;
  end
  @(posedge clk)
  A <= 4'd2;

  confirm <= 1'b1;
  repeat(3) begin
    @(posedge clk)
    confirm <= 1'b1;
  end
  @(posedge clk)
  A <= 4'd8;

  confirm <= 1'b1;
  repeat(3) begin
    @(posedge clk)
    confirm <= 1'b1;
  end
  @(posedge clk)
  A <= 4'd1;

  confirm <= 1'b1;
  repeat(3) begin
    @(posedge clk)
    confirm <= 1'b1;
  end
  @(posedge clk)
  A <= 4'd1;
  confirm <= 1'b0;

  setup <= 1'b1;
  repeat(3) begin
    @(posedge clk)
    setup <= 1'b1;
  end
  @(posedge clk)
  setup <= 1'b0;

  // 测试输入错误的密码
  ready <= 1'b1;
  repeat(3) begin
    @(posedge clk)
    ready <= 1'b1;
  end
  @(posedge clk)
  ready <= 1'b0;

  confirm <= 1'b1;
  repeat(3) begin
    @(posedge clk)
    confirm <= 1'b1;
  end
  @(posedge clk)
  A <= 4'd3;

  confirm <= 1'b1;
  repeat(3) begin
    @(posedge clk)
    confirm <= 1'b1;
  end
  @(posedge clk)
  A <= 4'd2;

  confirm <= 1'b1;
  repeat(3) begin
    @(posedge clk)
    confirm <= 1'b1;
  end
  @(posedge clk)
  A <= 4'd8;

  confirm <= 1'b1;
  repeat(3) begin
    @(posedge clk)
    confirm <= 1'b1;
  end
  @(posedge clk)
  A <= 4'd1;
  confirm <= 1'b0;

  sure <= 1'b1;
  repeat(3) begin
    @(posedge clk)
    sure <= 1'b1;
  end
  @(posedge clk)
  sure <= 1'b0;

  setup <= 1'b1;
  repeat(3) begin
    @(posedge clk)
    setup <= 1'b1;
  end
  @(posedge clk)
  setup <= 1'b0;

  #200
  $finish;
end


top #(
  .KEY_CNT_MAX  (4),
  .RT_CNT_MAX   (1),
  .DISP_COUNT   (1)
) dut(
  .clk      (clk    ),
  .rst      (rst    ),
  .wait_t   (wait_t ),
  .setup    (setup  ),
  .ready    (ready  ),
  .fire     (fire   ),
  .sure     (sure   ),
  .A        (A      ),
  .confirm  (confirm),
  .sel      (sel    ),
  .lt       (lt     ),
  .bt       (bt     ),
  .rt       (rt     ),
  .m_disp   (m_disp )
);

endmodule

src/rtl/wave.vcd
$date
	Sun Jan 15 22:13:10 2023
$end
$version
	Icarus Verilog
$end
$timescale
	1ps
$end
$scope module top_tb $end
$var wire 4 ! sel [3:0] $end
$var wire 1 " rt $end
$var wire 7 # m_disp [6:0] $end
$var wire 1 $ lt $end
$var wire 1 % bt $end
$var reg 4 & A [3:0] $end
$var reg 1 ' clk $end
$var reg 1 ( confirm $end
$var reg 1 ) fire $end
$var reg 1 * ready $end
$var reg 1 + rst $end
$var reg 1 , setup $end
$var reg 1 - sure $end
$var reg 1 . wait_t $end
$scope module dut $end
$var wire 4 / A [3:0] $end
$var wire 1 ' clk $end
$var wire 1 ( confirm $end
$var wire 1 ) fire $end
$var wire 1 * ready $end
$var wire 1 + rst $end
$var wire 1 , setup $end
$var wire 1 - sure $end
$var wire 1 . wait_t $end
$var wire 4 0 sel [3:0] $end
$var wire 1 1 rt_en $end
$var wire 1 " rt $end
$var wire 16 2 passport [15:0] $end
$var wire 7 3 m_disp [6:0] $end
$var wire 1 $ lt $end
$var wire 1 4 disp_en $end
$var wire 1 5 db_wait_t $end
$var wire 1 6 db_sure $end
$var wire 1 7 db_setup $end
$var wire 1 8 db_ready $end
$var wire 1 9 db_fire $end
$var wire 1 : db_confirm $end
$var wire 1 % bt $end
$scope module confirm_db $end
$var wire 1 ' clk $end
$var wire 1 : debounced_key $end
$var wire 1 ( key $end
$var wire 1 + rst $end
$var reg 32 ; cnt [31:0] $end
$var reg 1 < key_flag $end
$upscope $end
$scope module fire_db $end
$var wire 1 ' clk $end
$var wire 1 ) key $end
$var wire 1 + rst $end
$var wire 1 9 debounced_key $end
$var reg 32 = cnt [31:0] $end
$var reg 1 9 key_flag $end
$upscope $end
$scope module numeric_code_detonator_inst $end
$var wire 4 > A [3:0] $end
$var wire 1 ? any_input $end
$var wire 1 ' clk $end
$var wire 1 : confirm $end
$var wire 1 4 disp_en $end
$var wire 1 9 fire $end
$var wire 1 + rst $end
$var wire 1 5 wait_t $end
$var wire 1 6 sure $end
$var wire 1 7 setup $end
$var wire 1 1 rt_en $end
$var wire 1 8 ready $end
$var wire 1 $ lt $end
$var wire 1 % bt $end
$var reg 4 @ current_state [3:0] $end
$var reg 4 A next_state [3:0] $end
$var reg 16 B passport [15:0] $end
$var reg 4 C ptr [3:0] $end
$upscope $end
$scope module ready_db $end
$var wire 1 ' clk $end
$var wire 1 * key $end
$var wire 1 + rst $end
$var wire 1 8 debounced_key $end
$var reg 32 D cnt [31:0] $end
$var reg 1 8 key_flag $end
$upscope $end
$scope module setup_db $end
$var wire 1 ' clk $end
$var wire 1 7 debounced_key $end
$var wire 1 , key $end
$var wire 1 + rst $end
$var reg 32 E cnt [31:0] $end
$var reg 1 F key_flag $end
$upscope $end
$scope module sure_db $end
$var wire 1 ' clk $end
$var wire 1 - key $end
$var wire 1 + rst $end
$var wire 1 6 debounced_key $end
$var reg 32 G cnt [31:0] $end
$var reg 1 6 key_flag $end
$upscope $end
$scope module u_disp_ctrl $end
$var wire 1 ' clk $end
$var wire 16 H data [15:0] $end
$var wire 1 4 en $end
$var wire 1 + rst $end
$var wire 4 I sel [3:0] $end
$var reg 1 J clk_out $end
$var reg 16 K count [15:0] $end
$var reg 4 L current_input [3:0] $end
$var reg 7 M m_disp [6:0] $end
$var reg 4 N sel_n [3:0] $end
$upscope $end
$scope module u_red_led $end
$var wire 1 ' clk $end
$var wire 1 1 en $end
$var wire 1 + rst $end
$var wire 1 " rt $end
$var reg 32 O cnt [31:0] $end
$var reg 1 P rt_tmp $end
$upscope $end
$scope module wait_db $end
$var wire 1 ' clk $end
$var wire 1 . key $end
$var wire 1 + rst $end
$var wire 1 5 debounced_key $end
$var reg 32 Q cnt [31:0] $end
$var reg 1 5 key_flag $end
$upscope $end
$upscope $end
$upscope $end
$enddefinitions $end
#0
$dumpvars
bx Q
xP
bx O
bx N
bx M
bx L
bx K
xJ
bx I
bx H
bx G
xF
bx E
bx D
bx C
bx B
bx A
bx @
x?
bx >
bx =
x<
bx ;
x:
x9
x8
x7
x6
x5
x4
bx 3
bx 2
x1
bx 0
bx /
0.
0-
0,
1+
0*
0)
0(
0'
bx &
x%
x$
bx #
x"
bx !
$end
#10
b1000 N
b1111 !
b1111 0
b1111 I
04
0?
b1 #
b1 3
b1 M
0"
b0 A
b0 L
b0 Q
05
b0 E
07
0F
b0 D
08
b0 =
09
b0 G
06
b0 ;
0:
0<
1J
b0 K
b0 O
0P
01
0$
0%
b0 @
b1111 C
b0 2
b0 B
b0 H
1*
1'
#20
0+
0'
#30
0*
1P
0J
b1 D
1'
#40
0'
#50
b0 D
1J
0P
1*
1'
#60
0'
#70
1P
0J
b1 D
1'
#80
0'
#90
b10 D
1J
0P
1'
#100
0'
#110
1(
0*
1P
0J
b11 D
1'
#120
0'
#130
1?
b1 A
b0 D
18
b1 ;
1J
0P
1'
#140
0'
#150
0?
b1 @
1P
0J
b10 ;
08
1'
#160
0'
#170
b11 ;
1J
0P
1'
#180
0'
#190
b10 A
b10 &
b10 /
b10 >
1P
0J
1:
1<
b0 ;
1'
#200
0'
#210
b10010 #
b10010 3
b10010 M
b10 L
b111 !
b111 0
b111 I
14
b1 ;
0:
0<
1J
0P
b10 @
b1011 C
b10000000000000 2
b10000000000000 B
b10000000000000 H
1'
#220
0'
#230
1P
0J
b10 ;
1'
#240
0'
#250
b1 #
b1 3
b1 M
b0 L
b1011 !
b1011 0
b1011 I
b100 N
b11 ;
1J
0P
1'
#260
0'
#270
b11 A
b101 &
b101 /
b101 >
1P
0J
1:
1<
b0 ;
1'
#280
0'
#290
b1101 !
b1101 0
b1101 I
b10 N
b1 #
b1 3
b1 M
b0 L
b1 ;
0:
0<
1J
0P
b11 @
b111 C
b10010100000000 2
b10010100000000 B
b10010100000000 H
1'
#300
0'
#310
1P
0J
b10 ;
1'
#320
0'
#330
b1110 !
b1110 0
b1110 I
b1 N
b11 ;
1J
0P
1'
#340
0'
#350
b100 A
b1000 &
b1000 /
b1000 >
1P
0J
1:
1<
b0 ;
1'
#360
0'
#370
b10010 #
b10010 3
b10010 M
b10 L
b111 !
b111 0
b111 I
b1000 N
b1 ;
0:
0<
1J
0P
b100 @
b11 C
b10010110000000 2
b10010110000000 B
b10010110000000 H
1'
#380
0'
#390
1P
0J
b10 ;
1'
#400
0'
#410
b100100 #
b100100 3
b100100 M
b101 L
b1011 !
b1011 0
b1011 I
b100 N
b11 ;
1J
0P
1'
#420
0'
#430
b101 A
1-
0(
b0 &
b0 /
b0 >
1P
0J
1:
1<
b0 ;
1'
#440
0'
#450
b0 #
b0 3
b0 M
b1000 L
b1101 !
b1101 0
b1101 I
b10 N
b1 G
0:
0<
1J
0P
b101 @
b1111 C
1'
#460
0'
#470
1P
0J
b10 G
1'
#480
0'
#490
b1 #
b1 3
b1 M
b0 L
b1110 !
b1110 0
b1110 I
b1 N
b11 G
1J
0P
1'
#500
0'
#510
1?
b110 A
1)
0-
1P
0J
16
b0 G
1'
#520
0'
#530
b10010 #
b10010 3
b10010 M
b10 L
b111 !
b111 0
b111 I
b1000 N
0?
b1000 A
b1 =
06
1J
0P
b110 @
1'
#540
0'
#550
b1 #
b1 3
b1 M
b0 L
b1111 !
b1111 0
b1111 I
04
1$
b1000 @
1P
0J
b10 =
1'
#560
0'
#570
b11 =
1J
0P
1'
#580
0'
#590
1?
b1001 A
1.
0)
1P
0J
19
b0 =
1'
#600
0'
#610
0?
b1 Q
09
1J
0P
0$
1%
b1001 @
1'
#620
0'
#630
b0 2
b0 B
b0 H
1P
0J
b10 Q
1'
#640
0'
#650
b11 Q
1J
0P
1'
#660
0'
#670
1?
b0 A
1P
0J
15
b0 Q
1'
#680
0'
#690
0?
b1 Q
05
1J
0P
0%
b0 @
1'
#700
0'
#710
1P
0J
b10 Q
1'
#720
0'
#730
b11 Q
1J
0P
1'
#740
0'
#750
1?
1P
0J
15
b0 Q
1'
#760
0'
#770
0?
b1 Q
05
1J
0P
1'
#780
0'
#790
1P
0J
b10 Q
0.
1'
#800
0'
#810
b0 Q
1J
0P
1'
#820
0'
#830
1P
0J
1'
#840
0'
#850
1J
0P
1'
#860
0'
#870
1P
0J
1'
#880
0'
#890
1J
0P
1'
#900
0'
#910
1P
0J
1'
#920
0'
#930
1J
0P
1'
#940
0'
#950
1P
0J
1'
#960
0'
#970
1J
0P
1'
#980
0'
#990
1P
0J
1*
1'
#1000
0'
#1010
b1 D
1J
0P
1'
#1020
0'
#1030
1P
0J
b10 D
1'
#1040
0'
#1050
1(
0*
b11 D
1J
0P
1'
#1060
0'
#1070
1?
b1 A
1P
0J
b1 ;
18
b0 D
1'
#1080
0'
#1090
0?
08
b10 ;
1J
0P
b1 @
1'
#1100
0'
#1110
1P
0J
b11 ;
1'
#1120
0'
#1130
b10 A
1)
b10 &
b10 /
b10 >
0(
b0 ;
1:
1<
1J
0P
1'
#1140
0'
#1150
b10010 #
b10010 3
b10010 M
b10 L
b111 !
b111 0
b111 I
14
b1011 C
b10000000000000 2
b10000000000000 B
b10000000000000 H
b10 @
1P
0J
0:
0<
b1 =
1'
#1160
0'
#1170
b1 #
b1 3
b1 M
b0 L
b1011 !
b1011 0
b1011 I
b100 N
b10 =
1J
0P
1'
#1180
0'
#1190
1P
0J
b11 =
1'
#1200
0'
#1210
b1101 !
b1101 0
b1101 I
b10 N
1?
b111 A
1.
0)
b0 =
19
1J
0P
1'
#1220
0'
#1230
b1111 !
b1111 0
b1111 I
04
0?
1"
11
b111 @
1P
0J
09
b1 Q
1'
#1240
0'
#1250
0"
b10 Q
1J
0P
b1111 C
b0 2
b0 B
b0 H
1'
#1260
0'
#1270
1"
1P
0J
b11 Q
1'
#1280
0'
#1290
1?
0"
1,
0.
b0 Q
15
1J
0P
1'
#1300
0'
#1310
1"
0?
1P
0J
b1 E
05
1'
#1320
0'
#1330
0"
b10 E
1J
0P
1'
#1340
0'
#1350
1"
1P
0J
b11 E
1'
#1360
0'
#1370
b0 A
0"
1*
0,
b0 E
17
1F
1J
0P
1'
#1380
0'
#1390
01
b0 @
1P
0J
b1 D
07
0F
1'
#1400
0'
#1410
b10 D
1J
0P
1'
#1420
0'
#1430
1P
0J
b11 D
1'
#1440
0'
#1450
1?
b1 A
1(
0*
b0 D
18
1J
0P
1'
#1460
0'
#1470
0?
b1 @
1P
0J
b1 ;
08
1'
#1480
0'
#1490
b10 ;
1J
0P
1'
#1500
0'
#1510
1P
0J
b11 ;
1'
#1520
0'
#1530
b10 A
1-
0(
b0 ;
1:
1<
1J
0P
1'
#1540
0'
#1550
b1101 !
b1101 0
b1101 I
14
b1011 C
b10000000000000 2
b10000000000000 B
b10000000000000 H
b10 @
1P
0J
0:
0<
b1 G
1'
#1560
0'
#1570
b1110 !
b1110 0
b1110 I
b1 N
b10 G
1J
0P
1'
#1580
0'
#1590
1P
0J
b11 G
1'
#1600
0'
#1610
b10010 #
b10010 3
b10010 M
b10 L
b111 !
b111 0
b111 I
b1000 N
1?
b111 A
1,
0-
b0 G
16
1J
0P
1'
#1620
0'
#1630
b1 #
b1 3
b1 M
b0 L
b1111 !
b1111 0
b1111 I
04
0?
1"
11
b111 @
1P
0J
06
b1 E
1'
#1640
0'
#1650
0"
b10 E
1J
0P
b1111 C
b0 2
b0 B
b0 H
1'
#1660
0'
#1670
1"
1P
0J
b11 E
1'
#1680
0'
#1690
b0 A
0"
1*
0,
b0 E
17
1F
1J
0P
1'
#1700
0'
#1710
01
b0 @
1P
0J
b1 D
07
0F
1'
#1720
0'
#1730
b10 D
1J
0P
1'
#1740
0'
#1750
1P
0J
b11 D
1'
#1760
0'
#1770
1?
b1 A
1(
0*
b0 D
18
1J
0P
1'
#1780
0'
#1790
0?
b1 @
1P
0J
b1 ;
08
1'
#1800
0'
#1810
b10 ;
1J
0P
1'
#1820
0'
#1830
1P
0J
b11 ;
1'
#1840
0'
#1850
b10 A
b11 &
b11 /
b11 >
b0 ;
1:
1<
1J
0P
1'
#1860
0'
#1870
b110 #
b110 3
b110 M
b11 L
b111 !
b111 0
b111 I
14
b1011 C
b11000000000000 2
b11000000000000 B
b11000000000000 H
b10 @
1P
0J
0:
0<
b1 ;
1'
#1880
0'
#1890
b1 #
b1 3
b1 M
b0 L
b1011 !
b1011 0
b1011 I
b100 N
b10 ;
1J
0P
1'
#1900
0'
#1910
1P
0J
b11 ;
1'
#1920
0'
#1930
b1101 !
b1101 0
b1101 I
b10 N
b11 A
b10 &
b10 /
b10 >
b0 ;
1:
1<
1J
0P
1'
#1940
0'
#1950
b111 C
b11001000000000 2
b11001000000000 B
b11001000000000 H
b11 @
1P
0J
0:
0<
b1 ;
1'
#1960
0'
#1970
b1110 !
b1110 0
b1110 I
b1 N
b10 ;
1J
0P
1'
#1980
0'
#1990
1P
0J
b11 ;
1'
#2000
0'
